geohashr-1.5.0.dist-info/METADATA
geohashr-1.5.0.dist-info/WHEEL
geohashr-1.5.0.dist-info/licenses/LICENSE
geohashr/__init__.py
geohashr/_geohashr.cpython-311-arm-linux-gnueabihf.so
geohashr/_geohashr.pyi
geohashr/py.typed
geohashr-1.5.0.dist-info/RECORD
