Metadata-Version: 2.4
Name: geohashr
Version: 1.5.0
Classifier: Development Status :: 5 - Production/Stable
Classifier: Intended Audience :: Developers
Classifier: License :: OSI Approved :: BSD License
Classifier: Operating System :: MacOS
Classifier: Operating System :: Microsoft :: Windows
Classifier: Operating System :: POSIX :: Linux
Classifier: Programming Language :: Python :: 3
Classifier: Programming Language :: Python :: 3.9
Classifier: Programming Language :: Python :: 3.10
Classifier: Programming Language :: Python :: 3.11
Classifier: Programming Language :: Python :: 3.12
Classifier: Programming Language :: Python :: 3.13
Classifier: Programming Language :: Python :: Implementation :: CPython
Classifier: Programming Language :: Python :: Implementation :: PyPy
Classifier: Programming Language :: Python
Classifier: Programming Language :: Rust
Classifier: Topic :: Scientific/Engineering :: GIS
License-File: LICENSE
Summary: Just another geohashing library
Keywords: geohash,gis
Home-Page: https://github.com/gi0baro/geohashr
Author: Giovanni Barillari <g@baro.dev>, Paolo Quadri <pquadri10@gmail.com>
Author-email: Giovanni Barillari <g@baro.dev>, Paolo Quadri <pquadri10@gmail.com>
License: BSD-3-Clause
Requires-Python: >=3.9
Project-URL: Homepage, https://github.com/gi0baro/geohashr
Project-URL: Funding, https://github.com/sponsors/gi0baro
Project-URL: Source, https://github.com/gi0baro/geohashr
